onegov.wtfs-1.4.2-py3.6-nspkg.pth
onegov/wtfs/.gitignore
onegov/wtfs/__init__.py
onegov/wtfs/app.py
onegov/wtfs/cli.py
onegov/wtfs/path.py
onegov/wtfs/security.py
onegov/wtfs/upgrade.py
onegov/wtfs/assets/css/jquery.datetimepicker.css
onegov/wtfs/assets/css/react-dropdown-tree-select.css
onegov/wtfs/assets/css/tablesaw.css
onegov/wtfs/assets/js/common.js
onegov/wtfs/assets/js/confirm.jsx
onegov/wtfs/assets/js/datetimepicker.js
onegov/wtfs/assets/js/foundation.js
onegov/wtfs/assets/js/intercooler.js
onegov/wtfs/assets/js/jquery.datetimepicker.js
onegov/wtfs/assets/js/jquery.js
onegov/wtfs/assets/js/jquery.tablesorter.js
onegov/wtfs/assets/js/modernizr.js
onegov/wtfs/assets/js/react-dom.js
onegov/wtfs/assets/js/react.js
onegov/wtfs/assets/js/tablesaw-create.js
onegov/wtfs/assets/js/tablesaw-init.js
onegov/wtfs/assets/js/tablesaw.jquery.js
onegov/wtfs/assets/js/underscore.js
onegov/wtfs/collections/__init__.py
onegov/wtfs/collections/municipalities.py
onegov/wtfs/collections/notifications.py
onegov/wtfs/collections/payment_types.py
onegov/wtfs/collections/scan_jobs.py
onegov/wtfs/fields/__init__.py
onegov/wtfs/fields/hint.py
onegov/wtfs/fields/municipality.py
onegov/wtfs/forms/__init__.py
onegov/wtfs/forms/daily_list.py
onegov/wtfs/forms/invoice.py
onegov/wtfs/forms/municipality.py
onegov/wtfs/forms/notification.py
onegov/wtfs/forms/payment_type.py
onegov/wtfs/forms/report.py
onegov/wtfs/forms/scan_job.py
onegov/wtfs/forms/user.py
onegov/wtfs/forms/user_manual.py
onegov/wtfs/layouts/__init__.py
onegov/wtfs/layouts/daily_list.py
onegov/wtfs/layouts/default.py
onegov/wtfs/layouts/invoice.py
onegov/wtfs/layouts/mail.py
onegov/wtfs/layouts/municipality.py
onegov/wtfs/layouts/notification.py
onegov/wtfs/layouts/payment_type.py
onegov/wtfs/layouts/report.py
onegov/wtfs/layouts/scan_job.py
onegov/wtfs/layouts/user.py
onegov/wtfs/layouts/user_manual.py
onegov/wtfs/locale/de_CH/LC_MESSAGES/onegov.wtfs.po
onegov/wtfs/models/__init__.py
onegov/wtfs/models/daily_list.py
onegov.wtfs-1.4.2.dist-info/METADATA
onegov.wtfs-1.4.2.dist-info/WHEEL
onegov.wtfs-1.4.2.dist-info/entry_points.txt
onegov.wtfs-1.4.2.dist-info/namespace_packages.txt
onegov.wtfs-1.4.2.dist-info/top_level.txt
onegov.wtfs-1.4.2.dist-info/RECORD
