Metadata-Version: 2.1
Name: onegov.wtfs
Version: 1.4.2
Summary: Tax form scanning app for the city of Winterthur
Home-page: http://github.com/onegov/onegov.wtfs
Author: Seantis GmbH
Author-email: info@seantis.ch
License: GPLv2
Platform: any
Classifier: Intended Audience :: Developers
Classifier: Programming Language :: Python :: 3 :: Only
Classifier: Programming Language :: Python :: 3.6
Classifier: Programming Language :: Python :: 3.7
Classifier: Topic :: Software Development :: Libraries :: Python Modules
Classifier: License :: OSI Approved :: GNU General Public License v2 (GPLv2)
Requires-Python: >=3.6
Requires-Dist: arrow (>=0.8.0)
Requires-Dist: babel (>=2.6.0)
Requires-Dist: cached-property
Requires-Dist: cssmin
Requires-Dist: humanize
Requires-Dist: onegov.chat
Requires-Dist: onegov.core (>=v0.79.1)
Requires-Dist: onegov.file
Requires-Dist: onegov.form (>=0.46.1)
Requires-Dist: onegov.foundation
Requires-Dist: onegov.shared (>=0.3.0)
Requires-Dist: onegov.user
Requires-Dist: python-dateutil
Requires-Dist: requests
Requires-Dist: rjsmin
Provides-Extra: test
Requires-Dist: coverage ; extra == 'test'
Requires-Dist: freezegun ; extra == 'test'
Requires-Dist: mock ; extra == 'test'
Requires-Dist: onegov-testing ; extra == 'test'
Requires-Dist: pyquery ; extra == 'test'
Requires-Dist: pytest-localserver ; extra == 'test'
Requires-Dist: pytest (>=3.0.0) ; extra == 'test'
Requires-Dist: webtest ; extra == 'test'
